odoo/addons/sale_delivery_split_date/README.rst
odoo/addons/sale_delivery_split_date/__init__.py
odoo/addons/sale_delivery_split_date/__manifest__.py
odoo/addons/sale_delivery_split_date/i18n/ca.po
odoo/addons/sale_delivery_split_date/i18n/es.po
odoo/addons/sale_delivery_split_date/i18n/it.po
odoo/addons/sale_delivery_split_date/i18n/pt_PT.po
odoo/addons/sale_delivery_split_date/i18n/sale_delivery_split_date.pot
odoo/addons/sale_delivery_split_date/models/__init__.py
odoo/addons/sale_delivery_split_date/models/sale_order_line.py
odoo/addons/sale_delivery_split_date/readme/CONTRIBUTORS.md
odoo/addons/sale_delivery_split_date/readme/DESCRIPTION.md
odoo/addons/sale_delivery_split_date/readme/ROADMAP.md
odoo/addons/sale_delivery_split_date/static/description/icon.png
odoo/addons/sale_delivery_split_date/static/description/index.html
odoo/addons/sale_delivery_split_date/tests/__init__.py
odoo/addons/sale_delivery_split_date/tests/test_sale_delivery.py
odoo/addons/sale_delivery_split_date/views/stock_picking.xml
odoo_addon_sale_delivery_split_date-18.0.1.0.0.2.dist-info/METADATA
odoo_addon_sale_delivery_split_date-18.0.1.0.0.2.dist-info/WHEEL
odoo_addon_sale_delivery_split_date-18.0.1.0.0.2.dist-info/top_level.txt
odoo_addon_sale_delivery_split_date-18.0.1.0.0.2.dist-info/RECORD
