Metadata-Version: 2.1
Name: odoo-addon-sale_delivery_split_date
Version: 18.0.1.0.0.2
Requires-Python: >=3.10
Requires-Dist: odoo-addon-sale_order_line_date==18.0.*
Requires-Dist: odoo-addon-sale_procurement_group_by_line==18.0.*
Requires-Dist: odoo==18.0.*
Summary: Sale Deliveries split by date
Home-page: https://github.com/OCA/sale-workflow
License: AGPL-3
Author: Agile Business Group, Odoo Community Association (OCA)
Author-email: support@odoo-community.org
Classifier: Programming Language :: Python
Classifier: Framework :: Odoo
Classifier: Framework :: Odoo :: 18.0
Classifier: License :: OSI Approved :: GNU Affero General Public License v3
